malscan/__init__.py
malscan/dynamic_analysis.py
malscan/export_features.py
malscan/static_analysis.py
malscan-0.1.0.dist-info/METADATA
malscan-0.1.0.dist-info/WHEEL
malscan-0.1.0.dist-info/top_level.txt
malscan-0.1.0.dist-info/RECORD
